mojxml/LICENSE.txt
mojxml/__init__.py
mojxml/__main__.py
mojxml/constants.py
mojxml/parse.py
mojxml/reader.py
mojxml/schema.py
mojxml/process/__init__.py
mojxml/process/executor.py
mojxml-0.5.4.dist-info/METADATA
mojxml-0.5.4.dist-info/WHEEL
mojxml-0.5.4.dist-info/entry_points.txt
mojxml-0.5.4.dist-info/licenses/LICENSE.txt
mojxml-0.5.4.dist-info/RECORD
