Metadata-Version: 2.4
Name: mojxml
Version: 0.5.4
Summary: A tool for fast conversion of Japanese "MOJ Map XML" (land registration polygons) into geospatial formats.
Project-URL: Homepage, https://github.com/MIERUNE/mojxml-py
Project-URL: Repository, https://github.com/MIERUNE/mojxml-py
Author-email: Taku Fukada <naninunenor@gmail.com>, "MIERUNE Inc." <info@mierune.co.jp>
License-Expression: MIT
License-File: LICENSE.txt
Classifier: Intended Audience :: Developers
Classifier: Intended Audience :: Science/Research
Classifier: Operating System :: OS Independent
Classifier: Topic :: Scientific/Engineering :: GIS
Classifier: Topic :: Software Development :: Libraries :: Python Modules
Requires-Python: >=3.10.0
Requires-Dist: click>=8.1.8
Requires-Dist: fiona>=1.10.0
Requires-Dist: lxml>=4.9.2
Requires-Dist: pyproj>=3.7.1
